data_pipeline_avro_util/__init__.py
data_pipeline_avro_util/avro_builder.py
data_pipeline_avro_util/avro_string_reader.py
data_pipeline_avro_util/avro_string_writer.py
data_pipeline_avro_util/util.py
data_pipeline_avro_util/data_pipeline/__init__.py
data_pipeline_avro_util/data_pipeline/avro_meta_data.py
data_pipeline_avro_util/testing_helpers/__init__.py
data_pipeline_avro_util/testing_helpers/generate_payload_data.py
data_pipeline_avro_util-0.2.3.dist-info/DESCRIPTION.rst
data_pipeline_avro_util-0.2.3.dist-info/METADATA
data_pipeline_avro_util-0.2.3.dist-info/RECORD
data_pipeline_avro_util-0.2.3.dist-info/WHEEL
data_pipeline_avro_util-0.2.3.dist-info/metadata.json
data_pipeline_avro_util-0.2.3.dist-info/top_level.txt
