Metadata-Version: 2.0
Name: data-pipeline-avro-util
Version: 0.2.3
Summary: Common functionality build on top of Apache Avro
Home-page: https://github.com/Yelp/data_pipeline_avro_util
Author: Josh Szepietowski
Author-email: joshszep@yelp.com
License: UNKNOWN
Keywords: d,a,t,a,_,p,i,p,e,l,i,n,e,_,a,v,r,o,_,u,t,i,l
Platform: UNKNOWN
Classifier: Development Status :: 2 - Pre-Alpha
Classifier: Intended Audience :: Developers
Classifier: Natural Language :: English
Classifier: Programming Language :: Python :: 2
Classifier: Programming Language :: Python :: 2.6
Classifier: Programming Language :: Python :: 2.7
Classifier: Programming Language :: Python :: 3
Classifier: Programming Language :: Python :: 3.3
Classifier: Programming Language :: Python :: 3.4
Classifier: Programming Language :: Python :: Implementation :: PyPy
Requires-Dist: cached-property (>=0.1.5)
Requires-Dist: yelp-avro (==1.9.2)
